setup.py
lusmu/__init__.py
lusmu/core.py
lusmu/vector.py
lusmu/visualization.py
lusmu.egg-info/PKG-INFO
lusmu.egg-info/SOURCES.txt
lusmu.egg-info/dependency_links.txt
lusmu.egg-info/top_level.txt