Metadata-Version: 1.0
Name: lusmu
Version: 0.2
Summary: A lazy/forced evaluation library
Home-page: https://github.com/akaihola/lusmu
Author: Antti Kaihola
Author-email: antti.kaihola@eniram.fi
License: BSD
Keywords: eniram reactive lazy evaluation
Platform: UNKNOWN
